better_git_of_theseus-0.5.0.dist-info/licenses/LICENSE
git_of_theseus/__init__.py
git_of_theseus/analyze.py
git_of_theseus/app.py
git_of_theseus/cmd.py
git_of_theseus/line_plot.py
git_of_theseus/plotly_plots.py
git_of_theseus/stack_plot.py
git_of_theseus/survival_plot.py
git_of_theseus/utils.py
better_git_of_theseus-0.5.0.dist-info/METADATA
better_git_of_theseus-0.5.0.dist-info/WHEEL
better_git_of_theseus-0.5.0.dist-info/entry_points.txt
better_git_of_theseus-0.5.0.dist-info/top_level.txt
better_git_of_theseus-0.5.0.dist-info/RECORD
