Metadata-Version: 2.4
Name: better-git-of-theseus
Version: 0.5.0
Summary: Plot stats on Git repositories with interactive Plotly charts
Home-page: https://github.com/onewesong/better-git-of-theseus
Author: Erik Bernhardsson
Author-email: mail@erikbern.com
License-File: LICENSE
Requires-Dist: gitpython
Requires-Dist: numpy
Requires-Dist: tqdm
Requires-Dist: wcmatch
Requires-Dist: pygments
Requires-Dist: plotly
Requires-Dist: streamlit
Requires-Dist: python-dateutil
Requires-Dist: scipy
Requires-Dist: matplotlib
Dynamic: author
Dynamic: author-email
Dynamic: description
Dynamic: description-content-type
Dynamic: home-page
Dynamic: license-file
Dynamic: requires-dist
Dynamic: summary
